{"cameraMode":{"drawMode":0,"name":"Shaded","section":"Shading Mode"},"sceneLighting":true,"audioPlay":false,"sceneViewState":{"m_AlwaysRefresh":false,"showFog":true,"showSkybox":true,"showFlares":true,"showImageEffects":true,"showParticleSystems":true,"showVisualEffectGraphs":true,"m_FxEnabled":true},"in2DMode":false,"pivot":{"x":-50.192726135253909,"y":1.5885200500488282,"z":26.532089233398439},"rotation":{"x":-0.018361877650022508,"y":0.9316895008087158,"z":-0.047555167227983478,"w":-0.3596707582473755},"size":9.020648002624512,"orthographic":false}