{"cameraMode":{"drawMode":0,"name":"Shaded","section":"Shading Mode"},"sceneLighting":true,"audioPlay":false,"sceneViewState":{"m_AlwaysRefresh":false,"showFog":true,"showSkybox":true,"showFlares":true,"showImageEffects":true,"showParticleSystems":true,"showVisualEffectGraphs":true,"m_FxEnabled":true},"in2DMode":false,"pivot":{"x":-50.042633056640628,"y":2.609480619430542,"z":23.439842224121095},"rotation":{"x":-0.020195966586470605,"y":0.9198659062385559,"z":-0.04778128117322922,"w":-0.38879290223121645},"size":5.41921329498291,"orthographic":false}